./.gitignore
./PKG-INFO
./README.md
./main.py
./pyproject.toml
truffle_ai_music_creator_mcp-1.0.3.dist-info/METADATA
truffle_ai_music_creator_mcp-1.0.3.dist-info/WHEEL
truffle_ai_music_creator_mcp-1.0.3.dist-info/entry_points.txt
truffle_ai_music_creator_mcp-1.0.3.dist-info/RECORD
