Metadata-Version: 2.4
Name: truffle-ai-music-creator-mcp
Version: 1.0.3
Summary: MCP server for core music creation and audio processing operations
Author-email: Truffle AI <founders@trytruffle.ai>
Requires-Python: >=3.10
Requires-Dist: librosa>=0.10.0
Requires-Dist: mcp>=1.0.0
Requires-Dist: music21>=8.1.0
Requires-Dist: numpy>=1.24.0
Requires-Dist: pretty-midi>=0.2.9
Requires-Dist: pydub>=0.25.1
Requires-Dist: setuptools>=65.0.0
Provides-Extra: dev
Requires-Dist: black>=23.0.0; extra == 'dev'
Requires-Dist: jupyter>=1.0.0; extra == 'dev'
Requires-Dist: pytest>=7.0.0; extra == 'dev'
Requires-Dist: ruff>=0.1.0; extra == 'dev'
